{
  "episodes": [
    {
      "rank": 1,
      "title": "Blink",
      "series": 3,
      "era": "Modern",
      "broadcast_date": "2007-06-09",
      "director": "Hettie MacDonald",
      "writer": "Steven Moffat",
      "plot": "Sally Sparrow receives a mysterious message from the Doctor via a DVD easter egg and must navigate the Weeping Angels to save him.",
      "doctor": {
        "actor": "David Tennant",
        "incarnation": "Tenth Doctor"
      },
      "companion": {
        "actor": "Freema Agyeman",
        "character": "Martha Jones"
      },
      "cast": [
        {
          "actor": "Carey Mulligan",
          "character": "Sally Sparrow"
        },
        {
          "actor": "Lucy Gaskell",
          "character": "Kathy Nightingale"
        }
      ]
    },
    {
      "rank": 2,
      "title": "Heaven Sent",
      "series": 9,
      "era": "Modern",
      "broadcast_date": "2015-11-28",
      "director": "Rachel Talalay",
      "writer": "Steven Moffat",
      "plot": "The Doctor is trapped in a castle and must confront his deepest fears.",
      "doctor": {
        "actor": "Peter Capaldi",
        "incarnation": "Twelfth Doctor"
      },
      "companion": null,
      "cast": []
    },
    {
      "rank": 3,
      "title": "The Doctor's Wife",
      "series": 6,
      "era": "Modern",
      "broadcast_date": "May 14, 2011",
      "director": "Richard Clark",
      "writer": "Neil Gaiman & Steven Moffat",
      "plot": "The TARDIS matrix is transferred into a human body.",
      "doctor": {
        "actor": "Matt Smith",
        "incarnation": "Eleventh Doctor"
      },
      "companion": {
        "actor": "Karen Gillan",
        "character": "Amy Pond"
      },
      "cast": [
        {
          "actor": "Suranne Jones",
          "character": "Idris"
        }
      ]
    },
    {
      "rank": 4,
      "title": "Genesis of the \"Daleks\"",
      "series": 12,
      "era": "Classic",
      "broadcast_date": "08/03/1975",
      "director": "David Maloney",
      "writer": "Terry Nation",
      "plot": "The Doctor is sent by the Time Lords to prevent the creation of the Daleks.",
      "doctor": {
        "actor": "Tom Baker",
        "incarnation": "Fourth Doctor"
      },
      "companion": {
        "actor": "Elisabeth Sladen",
        "character": "Sarah Jane Smith"
      },
      "cast": [
        {
          "actor": "Michael Wisher",
          "character": "Davros"
        }
      ]
    },
    {
      "rank": 0,
      "title": "The Power of the Doctor",
      "series": null,
      "era": "Recent",
      "broadcast_date": "2022",
      "director": "Jamie Magnus Stone",
      "writer": "Chris Chibnall",
      "plot": "The Thirteenth Doctor's final adventure.",
      "doctor": {
        "actor": "Jodie Whittaker",
        "incarnation": "Thirteenth Doctor"
      },
      "companion": {
        "actor": "Mandip Gill",
        "character": "Yasmin Khan"
      },
      "cast": [
        {
          "actor": "Bradley Walsh",
          "character": "Graham O'Brien"
        }
      ]
    },
    {
      "rank": 6,
      "title": "Bad Wolf / The Parting of the Ways",
      "series": 1,
      "era": "Modern",
      "broadcast_date": "18/06/2005",
      "director": "Joe Ahearne",
      "writer": "Russell T Davies and Phil Ford",
      "plot": "The Doctor faces an army of Daleks in a battle for Earth.",
      "doctor": {
        "actor": "Christopher Eccleston",
        "incarnation": "Ninth Doctor"
      },
      "companion": {
        "actor": "Billie Piper",
        "character": "Rose Tyler"
      },
      "cast": []
    },
    {
      "rank": -1,
      "title": "The Day of the Doctor",
      "series": 7,
      "era": "Modern",
      "broadcast_date": "November 23, 2013",
      "director": "Nick Hurran",
      "writer": "Steven Moffat",
      "plot": "The Doctors unite to save Gallifrey.",
      "doctor": {
        "actor": "Matt Smith & David Tennant",
        "incarnation": "Eleventh & Tenth Doctors"
      },
      "companion": {
        "actor": "Jenna Coleman",
        "character": "Clara Oswald"
      },
      "cast": [
        {
          "actor": "John Hurt",
          "character": "War Doctor"
        }
      ]
    },
    {
      "rank": 8,
      "series": 14,
      "era": "Recent",
      "broadcast_date": "2026-12-25",
      "director": "Rachel Talalay",
      "writer": "Russell T Davies",
      "plot": "The Doctor faces a new threat.",
      "doctor": {
        "actor": "Ncuti Gatwa",
        "incarnation": "Fifteenth Doctor"
      },
      "companion": {
        "actor": "Millie Gibson",
        "character": "Ruby Sunday"
      },
      "cast": [
        {
          "actor": "Unknown Actor",
          "character": "Mystery Villain"
        }
      ]
    },
    {
      "rank": 9,
      "title": "El Doctor Misterioso",
      "series": 13,
      "era": "Recent",
      "broadcast_date": "2023-12-25",
      "director": "Señor Director",
      "writer": "María García & José López",
      "plot": "The Doctor visits ancient México.",
      "doctor": {
        "actor": "Ncuti Gatwa",
        "incarnation": "Decimoquinto Doctor"
      },
      "companion": null,
      "cast": [
        {
          "actor": "Pedro Almodóvar",
          "character": "El Guía"
        }
      ]
    }
  ]
}